numpyro_ext/__init__.py
numpyro_ext/distributions.py
numpyro_ext/infer.py
numpyro_ext/info.py
numpyro_ext/linear_op.py
numpyro_ext/optim.py
numpyro_ext/version.py
numpyro_ext-0.0.4.dist-info/LICENSE
numpyro_ext-0.0.4.dist-info/METADATA
numpyro_ext-0.0.4.dist-info/WHEEL
numpyro_ext-0.0.4.dist-info/top_level.txt
numpyro_ext-0.0.4.dist-info/RECORD
