Metadata-Version: 2.1
Name: numpyro-ext
Version: 0.0.4
Summary: A miscellaneous set of helper functions, custom distributions, and other utilities that I find useful when using NumPyro in my work
Author-email: Dan Foreman-Mackey <foreman.mackey@gmail.com>
License: Apache License
Project-URL: Homepage, https://github.com/dfm/numpyro-ext
Project-URL: Source, https://github.com/dfm/numpyro-ext
Project-URL: Bug Tracker, https://github.com/dfm/numpyro-ext/issues
Classifier: Operating System :: OS Independent
Classifier: Programming Language :: Python :: 3
Classifier: Development Status :: 4 - Beta
Classifier: License :: OSI Approved :: Apache Software License
Requires-Python: >=3.9
License-File: LICENSE
Requires-Dist: numpyro >=0.13.1
Provides-Extra: docs
Provides-Extra: ncx2
Requires-Dist: tensorflow-probability ; extra == 'ncx2'
Provides-Extra: test
Requires-Dist: pytest ; extra == 'test'
Requires-Dist: jaxopt ; extra == 'test'
Requires-Dist: typing-extensions ; extra == 'test'
